LICENSE
MANIFEST.in
setup.py
bin/kokki
kokki/__init__.py
kokki/base.py
kokki/command.py
kokki/environment.py
kokki/exceptions.py
kokki/kitchen.py
kokki/source.py
kokki/system.py
kokki/utils.py
kokki/version.py
kokki.egg-info/PKG-INFO
kokki.egg-info/SOURCES.txt
kokki.egg-info/dependency_links.txt
kokki.egg-info/requires.txt
kokki.egg-info/top_level.txt
kokki/cookbooks/__init__.py
kokki/providers/__init__.py
kokki/providers/accounts.py
kokki/providers/mount.py
kokki/providers/system.py
kokki/providers/package/__init__.py
kokki/providers/package/apt.py
kokki/providers/package/easy_install.py
kokki/providers/package/emerge.py
kokki/providers/package/yumrpm.py
kokki/providers/service/__init__.py
kokki/providers/service/debian.py
kokki/providers/service/gentoo.py
kokki/providers/service/redhat.py
kokki/resources/__init__.py
kokki/resources/accounts.py
kokki/resources/packaging.py
kokki/resources/service.py
kokki/resources/system.py
tests/__init__.py