Metadata-Version: 1.0
Name: kokki
Version: 0.4.1
Summary: Kokki is a system configuration management framework influenced by Chef
Home-page: http://samuelks.com/kokki/
Author: Samuel Stauffer
Author-email: samuel@descolada.com
License: UNKNOWN
Platform: UNKNOWN
Classifier: Intended Audience :: Developers
Classifier: License :: OSI Approved :: BSD License
Classifier: Operating System :: OS Independent
Classifier: Programming Language :: Python
Classifier: Topic :: Software Development :: Libraries :: Python Modules
